sim2x/__init__.py
sim2x/_cp2rg.py
sim2x/_sim2imp.py
sim2x/_version.py
sim2x/typing.py
sim2x/_cli/_cli.py
sim2x/_cli/_imp2seis.py
sim2x/_cli/_sim2imp.py
sim2x/_cli/_sim2rg.py
sim2x/_cli/config.py
sim2x/_sim2seis/__init__.py
sim2x/_sim2seis/_psf.py
sim2x/_sim2seis/_sim2seis.py
sim2x/_sim2seis/_wavelets.py
sim2x/utils/_cluster.py
sim2x/utils/tools.py
sim2x-0.1.dev14.dist-info/LICENSE
sim2x-0.1.dev14.dist-info/METADATA
sim2x-0.1.dev14.dist-info/WHEEL
sim2x-0.1.dev14.dist-info/entry_points.txt
sim2x-0.1.dev14.dist-info/top_level.txt
sim2x-0.1.dev14.dist-info/RECORD
