Metadata-Version: 2.1
Name: sim2x
Version: 0.1.dev14
Summary: Cornerpoint simulations to (2) something else (x)
Home-page: https://github.com/trhallam/sim2x/
Author-email: trhallam@gmail.com
License: MIT
Platform: UNKNOWN
Requires-Python: >=3.8
License-File: LICENSE
Requires-Dist: xarray
Requires-Dist: numpy
Requires-Dist: pandas
Requires-Dist: scipy
Requires-Dist: numba
Requires-Dist: dask
Requires-Dist: distributed
Requires-Dist: more-itertools
Requires-Dist: rich
Requires-Dist: pooch
Requires-Dist: pydantic
Requires-Dist: pydantic-yaml
Requires-Dist: ruamel.yaml
Requires-Dist: eclx (>=0.2)
Requires-Dist: digirock (>=0.1.2)
Requires-Dist: segysak
Requires-Dist: dataicer
Provides-Extra: docs
Requires-Dist: mkdocs ; extra == 'docs'
Requires-Dist: mkdocstrings ; extra == 'docs'
Requires-Dist: mkdocs-material ; extra == 'docs'
Requires-Dist: mkdocs-material-extensions ; extra == 'docs'
Requires-Dist: mkdocs-simple-plugin ; extra == 'docs'
Requires-Dist: mkdocs-jupyter ; extra == 'docs'
Requires-Dist: mkdocs-gen-files ; extra == 'docs'
Requires-Dist: mkdocs-include-markdown-plugin ; extra == 'docs'
Requires-Dist: mkautodoc ; extra == 'docs'
Requires-Dist: jupyterlab ; extra == 'docs'
Requires-Dist: matplotlib ; extra == 'docs'
Provides-Extra: test
Requires-Dist: pytest ; extra == 'test'
Requires-Dist: pytest-cov ; extra == 'test'
Requires-Dist: pandas ; extra == 'test'
Requires-Dist: numpy ; extra == 'test'
Requires-Dist: xarray ; extra == 'test'
Requires-Dist: hypothesis ; extra == 'test'
